[
  {
    "slug": "bai-tap-trac-nghiem-tu-vung-va-ngu-phap-tieng-anh-so-3",
    "exam_id": 7155,
    "name": "Bài tập trắc nghiệm từ vựng và ngữ pháp Tiếng Anh- Số #3",
    "matched": [
      "231259",
      "231260",
      "231261",
      "231262",
      "231263",
      "231264",
      "231265",
      "231266",
      "231267",
      "231268",
      "231269",
      "231270",
      "231271",
      "231272",
      "231273",
      "231274",
      "231275",
      "231276",
      "231277",
      "231278"
    ]
  },
  {
    "slug": "trac-nghiem-phan-biet-thi-hien-tai-don-va-thi-hien-tai-tiep-dien-tieng-anh-13",
    "exam_id": 5907,
    "name": "Bài tập trắc nghiệm phân biệt Thì hiện tại đơn và Thì hiện tại tiếp diễn",
    "matched": [
      "200261",
      "200262",
      "200263",
      "200264",
      "200265",
      "200266",
      "200267",
      "200268",
      "200269",
      "200270",
      "200271",
      "200272",
      "200273",
      "200274",
      "200275",
      "200276",
      "200277",
      "200278",
      "200279",
      "200280"
    ]
  },
  {
    "slug": "bai-tap-trac-nghiem-cau-bi-dong-online-de-3-tieng-anh-13",
    "exam_id": 5904,
    "name": "Bài tập trắc nghiệm câu bị động online - Đề #3",
    "matched": [
      "200201",
      "200202",
      "200203",
      "200204",
      "200205",
      "200206",
      "200207",
      "200208",
      "200209",
      "200210",
      "200211",
      "200212",
      "200213",
      "200214",
      "200215",
      "200216",
      "200217",
      "200218",
      "200219",
      "200220",
      "200221",
      "200222",
      "200223",
      "200224",
      "200225",
      "200226",
      "200227",
      "200228",
      "200229",
      "200230"
    ]
  },
  {
    "slug": "bai-tap-trac-nghiem-ve-gioi-tu-in-on-at-tieng-anh-13",
    "exam_id": 5880,
    "name": "Bài tập trắc nghiệm về giới từ in on at",
    "matched": [
      "199431",
      "199432",
      "199433",
      "199434",
      "199435",
      "199436",
      "199437",
      "199438",
      "199439",
      "199440"
    ]
  },
  {
    "slug": "bai-tap-trac-nghiem-phan-biet-rob-va-steal-tieng-anh-13",
    "exam_id": 4684,
    "name": "Bài tập trắc nghiệm phân biệt Rob và Steal",
    "matched": [
      "153012",
      "153013",
      "153014",
      "153015",
      "153016",
      "153017",
      "153018",
      "153019",
      "153020",
      "153021"
    ]
  },
  {
    "slug": "bai-tap-trac-nghiem-ve-dai-tu-quan-he-online-tieng-anh-13",
    "exam_id": 4683,
    "name": "Bài tập trắc nghiệm về Đại Từ Quan Hệ",
    "matched": [
      "153002",
      "153003",
      "153004",
      "153005",
      "153006",
      "153007",
      "153008",
      "153009",
      "153010",
      "153011"
    ]
  },
  {
    "slug": "bai-tap-mao-tu-tieng-anh-14",
    "exam_id": 189,
    "name": "Bài tập mạo từ Tiếng Anh #14",
    "matched": [
      "6592",
      "6593",
      "6594",
      "6595",
      "6596",
      "6597",
      "6598",
      "6599",
      "6600",
      "6601"
    ]
  },
  {
    "slug": "bai-tap-mao-tu-tieng-anh-13",
    "exam_id": 188,
    "name": "Bài tập mạo từ Tiếng Anh #13",
    "matched": [
      "6562",
      "6563",
      "6564",
      "6565",
      "6566",
      "6567",
      "6568",
      "6569",
      "6570",
      "6571",
      "6572",
      "6573",
      "6574",
      "6575",
      "6576",
      "6577",
      "6578",
      "6579",
      "6580",
      "6581",
      "6582",
      "6583",
      "6584",
      "6585",
      "6586",
      "6587",
      "6588",
      "6589",
      "6590",
      "6591"
    ]
  },
  {
    "slug": "bai-tap-mao-tu-tieng-anh-12",
    "exam_id": 187,
    "name": "Bài tập mạo từ Tiếng Anh #12",
    "matched": [
      "6532",
      "6533",
      "6534",
      "6535",
      "6536",
      "6537",
      "6538",
      "6539",
      "6540",
      "6541",
      "6542",
      "6543",
      "6544",
      "6545",
      "6546",
      "6547",
      "6548",
      "6549",
      "6550",
      "6551",
      "6552",
      "6553",
      "6554",
      "6555",
      "6556",
      "6557",
      "6558",
      "6559",
      "6560",
      "6561"
    ]
  },
  {
    "slug": "bai-tap-mao-tu-tieng-anh-11",
    "exam_id": 186,
    "name": "Bài tập mạo từ Tiếng Anh #11",
    "matched": [
      "6502",
      "6503",
      "6504",
      "6505",
      "6506",
      "6507",
      "6508",
      "6509",
      "6510",
      "6511",
      "6512",
      "6513",
      "6514",
      "6515",
      "6516",
      "6517",
      "6518",
      "6519",
      "6520",
      "6521",
      "6522",
      "6523",
      "6524",
      "6525",
      "6526",
      "6527",
      "6528",
      "6529",
      "6530",
      "6531"
    ]
  },
  {
    "slug": "bai-tap-mao-tu-tieng-anh-10",
    "exam_id": 185,
    "name": "Bài tập mạo từ Tiếng Anh #10",
    "matched": [
      "6472",
      "6473",
      "6474",
      "6475",
      "6476",
      "6477",
      "6478",
      "6479",
      "6480",
      "6481",
      "6482",
      "6483",
      "6484",
      "6485",
      "6486",
      "6487",
      "6488",
      "6489",
      "6490",
      "6491",
      "6492",
      "6493",
      "6494",
      "6495",
      "6496",
      "6497",
      "6498",
      "6499",
      "6500",
      "6501"
    ]
  },
  {
    "slug": "bai-tap-mao-tu-tieng-anh-9",
    "exam_id": 184,
    "name": "Bài tập mạo từ Tiếng Anh #9",
    "matched": [
      "6442",
      "6443",
      "6444",
      "6445",
      "6446",
      "6447",
      "6448",
      "6449",
      "6450",
      "6451",
      "6452",
      "6453",
      "6454",
      "6455",
      "6456",
      "6457",
      "6458",
      "6459",
      "6460",
      "6461",
      "6462",
      "6463",
      "6464",
      "6465",
      "6466",
      "6467",
      "6468",
      "6469",
      "6470",
      "6471"
    ]
  },
  {
    "slug": "bai-tap-mao-tu-tieng-anh-8",
    "exam_id": 183,
    "name": "Bài tập mạo từ Tiếng Anh #8",
    "matched": [
      "6412",
      "6413",
      "6414",
      "6415",
      "6416",
      "6417",
      "6418",
      "6419",
      "6420",
      "6421",
      "6422",
      "6423",
      "6424",
      "6425",
      "6426",
      "6427",
      "6428",
      "6429",
      "6430",
      "6431",
      "6432",
      "6433",
      "6434",
      "6435",
      "6436",
      "6437",
      "6438",
      "6439",
      "6440",
      "6441"
    ]
  },
  {
    "slug": "bai-tap-mao-tu-tieng-anh-7",
    "exam_id": 182,
    "name": "Bài tập mạo từ Tiếng Anh #7",
    "matched": [
      "6382",
      "6383",
      "6384",
      "6385",
      "6386",
      "6387",
      "6388",
      "6389",
      "6390",
      "6391",
      "6392",
      "6393",
      "6394",
      "6395",
      "6396",
      "6397",
      "6398",
      "6399",
      "6400",
      "6401",
      "6402",
      "6403",
      "6404",
      "6405",
      "6406",
      "6407",
      "6408",
      "6409",
      "6410",
      "6411"
    ]
  },
  {
    "slug": "bai-tap-mao-tu-tieng-anh-6",
    "exam_id": 181,
    "name": "Bài tập mạo từ Tiếng Anh #6",
    "matched": [
      "6352",
      "6353",
      "6354",
      "6355",
      "6356",
      "6357",
      "6358",
      "6359",
      "6360",
      "6361",
      "6362",
      "6363",
      "6364",
      "6365",
      "6366",
      "6367",
      "6368",
      "6369",
      "6370",
      "6371",
      "6372",
      "6373",
      "6374",
      "6375",
      "6376",
      "6377",
      "6378",
      "6379",
      "6380",
      "6381"
    ]
  },
  {
    "slug": "bai-tap-mao-tu-tieng-anh-5",
    "exam_id": 180,
    "name": "Bài tập mạo từ Tiếng Anh #5",
    "matched": [
      "6322",
      "6323",
      "6324",
      "6325",
      "6326",
      "6327",
      "6328",
      "6329",
      "6330",
      "6331",
      "6332",
      "6333",
      "6334",
      "6335",
      "6336",
      "6337",
      "6338",
      "6339",
      "6340",
      "6341",
      "6342",
      "6343",
      "6344",
      "6345",
      "6346",
      "6347",
      "6348",
      "6349",
      "6350",
      "6351"
    ]
  },
  {
    "slug": "bai-tap-mao-tu-tieng-anh-4",
    "exam_id": 179,
    "name": "Bài tập mạo từ Tiếng Anh #4",
    "matched": [
      "6292",
      "6293",
      "6294",
      "6295",
      "6296",
      "6297",
      "6298",
      "6299",
      "6300",
      "6301",
      "6302",
      "6303",
      "6304",
      "6305",
      "6306",
      "6307",
      "6308",
      "6309",
      "6310",
      "6311",
      "6312",
      "6313",
      "6314",
      "6315",
      "6316",
      "6317",
      "6318",
      "6319",
      "6320",
      "6321"
    ]
  },
  {
    "slug": "bai-tap-mao-tu-tieng-anh-3",
    "exam_id": 178,
    "name": "Bài tập mạo từ Tiếng Anh #3",
    "matched": [
      "6262",
      "6263",
      "6264",
      "6265",
      "6266",
      "6267",
      "6268",
      "6269",
      "6270",
      "6271",
      "6272",
      "6273",
      "6274",
      "6275",
      "6276",
      "6277",
      "6278",
      "6279",
      "6280",
      "6281",
      "6282",
      "6283",
      "6284",
      "6285",
      "6286",
      "6287",
      "6288",
      "6289",
      "6290",
      "6291"
    ]
  },
  {
    "slug": "bai-tap-mao-tu-tieng-anh-2",
    "exam_id": 177,
    "name": "Bài tập mạo từ Tiếng Anh #2",
    "matched": [
      "6232",
      "6233",
      "6234",
      "6235",
      "6236",
      "6237",
      "6238",
      "6239",
      "6240",
      "6241",
      "6242",
      "6243",
      "6244",
      "6245",
      "6246",
      "6247",
      "6248",
      "6249",
      "6250",
      "6251",
      "6252",
      "6253",
      "6254",
      "6255",
      "6256",
      "6257",
      "6258",
      "6259",
      "6260",
      "6261"
    ]
  },
  {
    "slug": "bai-tap-mao-tu-tieng-anh-online-1",
    "exam_id": 176,
    "name": "Bài tập mạo từ Tiếng Anh #1",
    "matched": [
      "6202",
      "6203",
      "6204",
      "6205",
      "6206",
      "6207",
      "6208",
      "6209",
      "6210",
      "6211",
      "6212",
      "6213",
      "6214",
      "6215",
      "6216",
      "6217",
      "6218",
      "6219",
      "6220",
      "6221",
      "6222",
      "6223",
      "6224",
      "6225",
      "6226",
      "6227",
      "6228",
      "6229",
      "6230",
      "6231"
    ]
  },
  {
    "slug": "bai-tap-trac-nghiem-tieng-anh-online-14",
    "exam_id": 175,
    "name": "Bài tập trắc nghiệm Tiếng Anh online #14",
    "matched": [
      "6192",
      "6193",
      "6194",
      "6195",
      "6196",
      "6197",
      "6198",
      "6199",
      "6200",
      "6201"
    ]
  },
  {
    "slug": "bai-tap-trac-nghiem-tieng-anh-online-13",
    "exam_id": 174,
    "name": "Bài tập trắc nghiệm Tiếng Anh online #13",
    "matched": [
      "6167",
      "6168",
      "6169",
      "6170",
      "6171",
      "6172",
      "6173",
      "6174",
      "6175",
      "6176",
      "6177",
      "6178",
      "6179",
      "6180",
      "6181",
      "6182",
      "6183",
      "6184",
      "6185",
      "6186",
      "6187",
      "6188",
      "6189",
      "6190",
      "6191"
    ]
  },
  {
    "slug": "bai-tap-trac-nghiem-tieng-anh-online-12",
    "exam_id": 173,
    "name": "Bài tập trắc nghiệm Tiếng Anh online #12",
    "matched": [
      "6142",
      "6143",
      "6144",
      "6145",
      "6146",
      "6147",
      "6148",
      "6149",
      "6150",
      "6151",
      "6152",
      "6153",
      "6154",
      "6155",
      "6156",
      "6157",
      "6158",
      "6159",
      "6160",
      "6161",
      "6162",
      "6163",
      "6164",
      "6165",
      "6166"
    ]
  },
  {
    "slug": "bai-tap-trac-nghiem-tieng-anh-online-11",
    "exam_id": 172,
    "name": "Bài tập trắc nghiệm Tiếng Anh online #11",
    "matched": [
      "6117",
      "6118",
      "6119",
      "6120",
      "6121",
      "6122",
      "6123",
      "6124",
      "6125",
      "6126",
      "6127",
      "6128",
      "6129",
      "6130",
      "6131",
      "6132",
      "6133",
      "6134",
      "6135",
      "6136",
      "6137",
      "6138",
      "6139",
      "6140",
      "6141"
    ]
  },
  {
    "slug": "bai-tap-trac-nghiem-tieng-anh-online-10",
    "exam_id": 171,
    "name": "Bài tập trắc nghiệm Tiếng Anh online #10",
    "matched": [
      "6092",
      "6093",
      "6094",
      "6095",
      "6096",
      "6097",
      "6098",
      "6099",
      "6100",
      "6101",
      "6102",
      "6103",
      "6104",
      "6105",
      "6106",
      "6107",
      "6108",
      "6109",
      "6110",
      "6111",
      "6112",
      "6113",
      "6114",
      "6115",
      "6116"
    ]
  },
  {
    "slug": "bai-tap-trac-nghiem-tieng-anh-online-9",
    "exam_id": 170,
    "name": "Bài tập trắc nghiệm Tiếng Anh online #9",
    "matched": [
      "6067",
      "6068",
      "6069",
      "6070",
      "6071",
      "6072",
      "6073",
      "6074",
      "6075",
      "6076",
      "6077",
      "6078",
      "6079",
      "6080",
      "6081",
      "6082",
      "6083",
      "6084",
      "6085",
      "6086",
      "6087",
      "6088",
      "6089",
      "6090",
      "6091"
    ]
  },
  {
    "slug": "bai-tap-trac-nghiem-tieng-anh-online-8",
    "exam_id": 169,
    "name": "Bài tập trắc nghiệm Tiếng Anh online #8",
    "matched": [
      "6042",
      "6043",
      "6044",
      "6045",
      "6046",
      "6047",
      "6048",
      "6049",
      "6050",
      "6051",
      "6052",
      "6053",
      "6054",
      "6055",
      "6056",
      "6057",
      "6058",
      "6059",
      "6060",
      "6061",
      "6062",
      "6063",
      "6064",
      "6065",
      "6066"
    ]
  },
  {
    "slug": "bai-tap-trac-nghiem-tieng-anh-online-7",
    "exam_id": 168,
    "name": "Bài tập trắc nghiệm Tiếng Anh online #7",
    "matched": [
      "6017",
      "6018",
      "6019",
      "6020",
      "6021",
      "6022",
      "6023",
      "6024",
      "6025",
      "6026",
      "6027",
      "6028",
      "6029",
      "6030",
      "6031",
      "6032",
      "6033",
      "6034",
      "6035",
      "6036",
      "6037",
      "6038",
      "6039",
      "6040",
      "6041"
    ]
  },
  {
    "slug": "bai-tap-trac-nghiem-tieng-anh-online-6",
    "exam_id": 167,
    "name": "Bài tập trắc nghiệm Tiếng Anh online #6",
    "matched": [
      "5992",
      "5993",
      "5994",
      "5995",
      "5996",
      "5997",
      "5998",
      "5999",
      "6000",
      "6001",
      "6002",
      "6003",
      "6004",
      "6005",
      "6006",
      "6007",
      "6008",
      "6009",
      "6010",
      "6011",
      "6012",
      "6013",
      "6014",
      "6015",
      "6016"
    ]
  },
  {
    "slug": "bai-tap-trac-nghiem-tieng-anh-online-5",
    "exam_id": 166,
    "name": "Bài tập trắc nghiệm Tiếng Anh online #5",
    "matched": [
      "5967",
      "5968",
      "5969",
      "5970",
      "5971",
      "5972",
      "5973",
      "5974",
      "5975",
      "5976",
      "5977",
      "5978",
      "5979",
      "5980",
      "5981",
      "5982",
      "5983",
      "5984",
      "5985",
      "5986",
      "5987",
      "5988",
      "5989",
      "5990",
      "5991"
    ]
  },
  {
    "slug": "bai-tap-trac-nghiem-tieng-anh-online-4",
    "exam_id": 165,
    "name": "Bài tập trắc nghiệm Tiếng Anh online #4",
    "matched": [
      "5942",
      "5943",
      "5944",
      "5945",
      "5946",
      "5947",
      "5948",
      "5949",
      "5950",
      "5951",
      "5952",
      "5953",
      "5954",
      "5955",
      "5956",
      "5957",
      "5958",
      "5959",
      "5960",
      "5961",
      "5962",
      "5963",
      "5964",
      "5965",
      "5966"
    ]
  },
  {
    "slug": "bai-tap-trac-nghiem-tieng-anh-online-3",
    "exam_id": 164,
    "name": "Bài tập trắc nghiệm Tiếng Anh online #3",
    "matched": [
      "5917",
      "5918",
      "5919",
      "5920",
      "5921",
      "5922",
      "5923",
      "5924",
      "5925",
      "5926",
      "5927",
      "5928",
      "5929",
      "5930",
      "5931",
      "5932",
      "5933",
      "5934",
      "5935",
      "5936",
      "5937",
      "5938",
      "5939",
      "5940",
      "5941"
    ]
  },
  {
    "slug": "bai-tap-trac-nghiem-tieng-anh-online-2",
    "exam_id": 163,
    "name": "Bài tập trắc nghiệm Tiếng Anh online #2",
    "matched": [
      "5892",
      "5893",
      "5894",
      "5895",
      "5896",
      "5897",
      "5898",
      "5899",
      "5900",
      "5901",
      "5902",
      "5903",
      "5904",
      "5905",
      "5906",
      "5907",
      "5908",
      "5909",
      "5910",
      "5911",
      "5912",
      "5913",
      "5914",
      "5915",
      "5916"
    ]
  },
  {
    "slug": "bai-tap-trac-nghiem-tieng-anh-online-1",
    "exam_id": 162,
    "name": "Bài tập trắc nghiệm Tiếng Anh online #1",
    "matched": [
      "5867",
      "5868",
      "5869",
      "5870",
      "5871",
      "5872",
      "5873",
      "5874",
      "5875",
      "5876",
      "5877",
      "5878",
      "5879",
      "5880",
      "5881",
      "5882",
      "5883",
      "5884",
      "5885",
      "5886",
      "5887",
      "5888",
      "5889",
      "5890",
      "5891"
    ]
  },
  {
    "slug": "bai-tap-trac-nghiem-kiem-tra-ngu-phap-tieng-anh-online-de-so-20",
    "exam_id": 161,
    "name": "Bài tập trắc nghiệm kiểm tra ngữ pháp Tiếng Anh online - Đề số #20",
    "matched": [
      "5842",
      "5843",
      "5844",
      "5845",
      "5846",
      "5847",
      "5848",
      "5849",
      "5850",
      "5851",
      "5852",
      "5853",
      "5854",
      "5855",
      "5856",
      "5857",
      "5858",
      "5859",
      "5860",
      "5861",
      "5862",
      "5863",
      "5864",
      "5865",
      "5866"
    ]
  },
  {
    "slug": "bai-tap-trac-nghiem-kiem-tra-ngu-phap-tieng-anh-online-de-so-19",
    "exam_id": 160,
    "name": "Bài tập trắc nghiệm kiểm tra ngữ pháp Tiếng Anh online - Đề số #19",
    "matched": [
      "5817",
      "5818",
      "5819",
      "5820",
      "5821",
      "5822",
      "5823",
      "5824",
      "5825",
      "5826",
      "5827",
      "5828",
      "5829",
      "5830",
      "5831",
      "5832",
      "5833",
      "5834",
      "5835",
      "5836",
      "5837",
      "5838",
      "5839",
      "5840",
      "5841"
    ]
  },
  {
    "slug": "bai-tap-trac-nghiem-kiem-tra-ngu-phap-tieng-anh-online-de-so-18",
    "exam_id": 159,
    "name": "Bài tập trắc nghiệm kiểm tra ngữ pháp Tiếng Anh online - Đề số #18",
    "matched": [
      "5792",
      "5793",
      "5794",
      "5795",
      "5796",
      "5797",
      "5798",
      "5799",
      "5800",
      "5801",
      "5802",
      "5803",
      "5804",
      "5805",
      "5806",
      "5807",
      "5808",
      "5809",
      "5810",
      "5811",
      "5812",
      "5813",
      "5814",
      "5815",
      "5816"
    ]
  },
  {
    "slug": "bai-tap-trac-nghiem-kiem-tra-ngu-phap-tieng-anh-online-de-so-17",
    "exam_id": 158,
    "name": "Bài tập trắc nghiệm kiểm tra ngữ pháp Tiếng Anh online - Đề số #17",
    "matched": [
      "5767",
      "5768",
      "5769",
      "5770",
      "5771",
      "5772",
      "5773",
      "5774",
      "5775",
      "5776",
      "5777",
      "5778",
      "5779",
      "5780",
      "5781",
      "5782",
      "5783",
      "5784",
      "5785",
      "5786",
      "5787",
      "5788",
      "5789",
      "5790",
      "5791"
    ]
  },
  {
    "slug": "bai-tap-trac-nghiem-kiem-tra-ngu-phap-tieng-anh-online-de-so-16",
    "exam_id": 157,
    "name": "Bài tập trắc nghiệm kiểm tra ngữ pháp Tiếng Anh online - Đề số #16",
    "matched": [
      "5742",
      "5743",
      "5744",
      "5745",
      "5746",
      "5747",
      "5748",
      "5749",
      "5750",
      "5751",
      "5752",
      "5753",
      "5754",
      "5755",
      "5756",
      "5757",
      "5758",
      "5759",
      "5760",
      "5761",
      "5762",
      "5763",
      "5764",
      "5765",
      "5766"
    ]
  },
  {
    "slug": "bai-tap-trac-nghiem-kiem-tra-ngu-phap-tieng-anh-online-de-so-15",
    "exam_id": 156,
    "name": "Bài tập trắc nghiệm kiểm tra ngữ pháp Tiếng Anh online - Đề số #15",
    "matched": [
      "5717",
      "5718",
      "5719",
      "5720",
      "5721",
      "5722",
      "5723",
      "5724",
      "5725",
      "5726",
      "5727",
      "5728",
      "5729",
      "5730",
      "5731",
      "5732",
      "5733",
      "5734",
      "5735",
      "5736",
      "5737",
      "5738",
      "5739",
      "5740",
      "5741"
    ]
  },
  {
    "slug": "bai-tap-trac-nghiem-kiem-tra-ngu-phap-tieng-anh-online-de-so-14",
    "exam_id": 155,
    "name": "Bài tập trắc nghiệm kiểm tra ngữ pháp Tiếng Anh online - Đề số #14",
    "matched": [
      "5692",
      "5693",
      "5694",
      "5695",
      "5696",
      "5697",
      "5698",
      "5699",
      "5700",
      "5701",
      "5702",
      "5703",
      "5704",
      "5705",
      "5706",
      "5707",
      "5708",
      "5709",
      "5710",
      "5711",
      "5712",
      "5713",
      "5714",
      "5715",
      "5716"
    ]
  },
  {
    "slug": "bai-tap-trac-nghiem-kiem-tra-ngu-phap-tieng-anh-online-de-so-13",
    "exam_id": 154,
    "name": "Bài tập trắc nghiệm kiểm tra ngữ pháp Tiếng Anh online - Đề số #13",
    "matched": [
      "5667",
      "5668",
      "5669",
      "5670",
      "5671",
      "5672",
      "5673",
      "5674",
      "5675",
      "5676",
      "5677",
      "5678",
      "5679",
      "5680",
      "5681",
      "5682",
      "5683",
      "5684",
      "5685",
      "5686",
      "5687",
      "5688",
      "5689",
      "5690",
      "5691"
    ]
  },
  {
    "slug": "bai-tap-trac-nghiem-kiem-tra-ngu-phap-tieng-anh-online-de-so-12",
    "exam_id": 153,
    "name": "Bài tập trắc nghiệm kiểm tra ngữ pháp Tiếng Anh online - Đề số #12",
    "matched": [
      "5642",
      "5643",
      "5644",
      "5645",
      "5646",
      "5647",
      "5648",
      "5649",
      "5650",
      "5651",
      "5652",
      "5653",
      "5654",
      "5655",
      "5656",
      "5657",
      "5658",
      "5659",
      "5660",
      "5661",
      "5662",
      "5663",
      "5664",
      "5665",
      "5666"
    ]
  },
  {
    "slug": "bai-tap-trac-nghiem-kiem-tra-ngu-phap-tieng-anh-online-de-so-11",
    "exam_id": 152,
    "name": "Bài tập trắc nghiệm kiểm tra ngữ pháp tiếng anh online - Đề số #11",
    "matched": [
      "5617",
      "5618",
      "5619",
      "5620",
      "5621",
      "5622",
      "5623",
      "5624",
      "5625",
      "5626",
      "5627",
      "5628",
      "5629",
      "5630",
      "5631",
      "5632",
      "5633",
      "5634",
      "5635",
      "5636",
      "5637",
      "5638",
      "5639",
      "5640",
      "5641"
    ]
  },
  {
    "slug": "bai-tap-trac-nghiem-kiem-tra-ngu-phap-tieng-anh-online-de-so-10",
    "exam_id": 151,
    "name": "Bài tập trắc nghiệm kiểm tra ngữ pháp tiếng anh online - Đề số #10",
    "matched": [
      "5592",
      "5593",
      "5594",
      "5595",
      "5596",
      "5597",
      "5598",
      "5599",
      "5600",
      "5601",
      "5602",
      "5603",
      "5604",
      "5605",
      "5606",
      "5607",
      "5608",
      "5609",
      "5610",
      "5611",
      "5612",
      "5613",
      "5614",
      "5615",
      "5616"
    ]
  },
  {
    "slug": "bai-tap-trac-nghiem-kiem-tra-ngu-phap-tieng-anh-online-de-so-9",
    "exam_id": 150,
    "name": "Bài tập trắc nghiệm kiểm tra ngữ pháp tiếng anh online - Đề số #9",
    "matched": [
      "5567",
      "5568",
      "5569",
      "5570",
      "5571",
      "5572",
      "5573",
      "5574",
      "5575",
      "5576",
      "5577",
      "5578",
      "5579",
      "5580",
      "5581",
      "5582",
      "5583",
      "5584",
      "5585",
      "5586",
      "5587",
      "5588",
      "5589",
      "5590",
      "5591"
    ]
  },
  {
    "slug": "bai-tap-trac-nghiem-kiem-tra-ngu-phap-tieng-anh-online-de-so-8",
    "exam_id": 149,
    "name": "Bài tập trắc nghiệm kiểm tra ngữ pháp tiếng anh online - Đề số #8",
    "matched": [
      "5542",
      "5543",
      "5544",
      "5545",
      "5546",
      "5547",
      "5548",
      "5549",
      "5550",
      "5551",
      "5552",
      "5553",
      "5554",
      "5555",
      "5556",
      "5557",
      "5558",
      "5559",
      "5560",
      "5561",
      "5562",
      "5563",
      "5564",
      "5565",
      "5566"
    ]
  },
  {
    "slug": "bai-tap-trac-nghiem-kiem-tra-ngu-phap-tieng-anh-online-de-so-7",
    "exam_id": 148,
    "name": "Bài tập trắc nghiệm kiểm tra ngữ pháp tiếng anh online - Đề số #7",
    "matched": [
      "5517",
      "5518",
      "5519",
      "5520",
      "5521",
      "5522",
      "5523",
      "5524",
      "5525",
      "5526",
      "5527",
      "5528",
      "5529",
      "5530",
      "5531",
      "5532",
      "5533",
      "5534",
      "5535",
      "5536",
      "5537",
      "5538",
      "5539",
      "5540",
      "5541"
    ]
  },
  {
    "slug": "bai-tap-trac-nghiem-kiem-tra-ngu-phap-tieng-anh-online-de-so-6",
    "exam_id": 147,
    "name": "Bài tập trắc nghiệm kiểm tra ngữ pháp tiếng anh online - Đề số #6",
    "matched": [
      "5492",
      "5493",
      "5494",
      "5495",
      "5496",
      "5497",
      "5498",
      "5499",
      "5500",
      "5501",
      "5502",
      "5503",
      "5504",
      "5505",
      "5506",
      "5507",
      "5508",
      "5509",
      "5510",
      "5511",
      "5512",
      "5513",
      "5514",
      "5515",
      "5516"
    ]
  },
  {
    "slug": "bai-tap-trac-nghiem-kiem-tra-ngu-phap-tieng-anh-online-de-so-5",
    "exam_id": 146,
    "name": "Bài tập trắc nghiệm kiểm tra ngữ pháp tiếng anh online - Đề số #5",
    "matched": [
      "5467",
      "5468",
      "5469",
      "5470",
      "5471",
      "5472",
      "5473",
      "5474",
      "5475",
      "5476",
      "5477",
      "5478",
      "5479",
      "5480",
      "5481",
      "5482",
      "5483",
      "5484",
      "5485",
      "5486",
      "5487",
      "5488",
      "5489",
      "5490",
      "5491"
    ]
  },
  {
    "slug": "bai-tap-trac-nghiem-kiem-tra-ngu-phap-tieng-anh-online-de-so-4",
    "exam_id": 145,
    "name": "Bài tập trắc nghiệm kiểm tra ngữ pháp tiếng anh online - Đề số #4",
    "matched": [
      "5442",
      "5443",
      "5444",
      "5445",
      "5446",
      "5447",
      "5448",
      "5449",
      "5450",
      "5451",
      "5452",
      "5453",
      "5454",
      "5455",
      "5456",
      "5457",
      "5458",
      "5459",
      "5460",
      "5461",
      "5462",
      "5463",
      "5464",
      "5465",
      "5466"
    ]
  },
  {
    "slug": "bai-tap-trac-nghiem-kiem-tra-ngu-phap-tieng-anh-online-de-so-3",
    "exam_id": 144,
    "name": "Bài tập trắc nghiệm kiểm tra ngữ pháp tiếng anh online - Đề số #3",
    "matched": [
      "5417",
      "5418",
      "5419",
      "5420",
      "5421",
      "5422",
      "5423",
      "5424",
      "5425",
      "5426",
      "5427",
      "5428",
      "5429",
      "5430",
      "5431",
      "5432",
      "5433",
      "5434",
      "5435",
      "5436",
      "5437",
      "5438",
      "5439",
      "5440",
      "5441"
    ]
  },
  {
    "slug": "bai-tap-trac-nghiem-kiem-tra-ngu-phap-tieng-anh-online-de-so-2",
    "exam_id": 143,
    "name": "Bài tập trắc nghiệm kiểm tra ngữ pháp tiếng anh online - Đề số #2",
    "matched": [
      "5392",
      "5393",
      "5394",
      "5395",
      "5396",
      "5397",
      "5398",
      "5399",
      "5400",
      "5401",
      "5402",
      "5403",
      "5404",
      "5405",
      "5406",
      "5407",
      "5408",
      "5409",
      "5410",
      "5411",
      "5412",
      "5413",
      "5414",
      "5415",
      "5416"
    ]
  },
  {
    "slug": "bai-trac-nghiem-kiem-tra-ngu-phap-tieng-anh-online-de-so-1",
    "exam_id": 142,
    "name": "Bài tập trắc nghiệm kiểm tra ngữ pháp tiếng anh online - Đề số #1",
    "matched": [
      "5367",
      "5368",
      "5369",
      "5370",
      "5371",
      "5372",
      "5373",
      "5374",
      "5375",
      "5376",
      "5377",
      "5378",
      "5379",
      "5380",
      "5381",
      "5382",
      "5383",
      "5384",
      "5385",
      "5386",
      "5387",
      "5388",
      "5389",
      "5390",
      "5391"
    ]
  },
  {
    "slug": "bai-tap-phan-biet-to-va-for-tieng-anh-13",
    "exam_id": 84,
    "name": "Bài tập phân biệt 'To' và 'For'",
    "matched": [
      "3061",
      "3062",
      "3063",
      "3064",
      "3065",
      "3066",
      "3067",
      "3068",
      "3069",
      "3070",
      "3857",
      "3858",
      "3859",
      "3860",
      "3861",
      "3862",
      "3863",
      "3864",
      "3865",
      "3866"
    ]
  },
  {
    "slug": "bai-tap-trac-nghiem-thi-qua-khu-tiep-dien-tieng-anh-13",
    "exam_id": 80,
    "name": "Bài tập trắc nghiệm thì quá khứ tiếp diễn (Past Continuous) online",
    "matched": [
      "2911",
      "2912",
      "2913",
      "2914",
      "2915",
      "2916",
      "2917",
      "2918",
      "2919",
      "2920"
    ]
  },
  {
    "slug": "bai-tap-trac-nghiem-thi-qua-khu-don-tieng-anh-13",
    "exam_id": 79,
    "name": "Bài tập trắc nghiệm thì quá khứ đơn #2",
    "matched": [
      "2900",
      "2901",
      "2902",
      "2903",
      "2904",
      "2905",
      "2906",
      "2907",
      "2908",
      "2909"
    ]
  },
  {
    "slug": "bai-tap-trac-nghiem-phan-biet-already-va-yet-tieng-anh-13",
    "exam_id": 77,
    "name": "Bài tập trắc nghiệm phân biệt 'Already' và 'Yet'",
    "matched": [
      "2863",
      "2864",
      "2865",
      "2866",
      "2867",
      "2868",
      "2869",
      "2870",
      "2871",
      "2872"
    ]
  },
  {
    "slug": "bai-tap-trac-nghiem-cau-chu-dong-va-bi-dong-muc-do-de-tieng-anh-13",
    "exam_id": 76,
    "name": "Bài tập trắc nghiệm câu chủ động và bị động - Mức độ dễ",
    "matched": [
      "2853",
      "2854",
      "2855",
      "2856",
      "2857",
      "2858",
      "2859",
      "2860",
      "2861",
      "2862"
    ]
  },
  {
    "slug": "bai-tap-trac-nghiem-phan-biet-because-va-because-of-tieng-anh-13",
    "exam_id": 65,
    "name": "Bài tập trắc nghiệm phân biệt 'because' và 'because of'",
    "matched": [
      "2363",
      "2364",
      "2365",
      "2366",
      "2367",
      "2368",
      "2369",
      "2370",
      "2371",
      "2372",
      "2373",
      "2374",
      "2375",
      "2376",
      "2377",
      "2378",
      "2379"
    ]
  },
  {
    "slug": "bai-tap-trac-nghiem-phan-biet-will-va-going-to-tieng-anh-13",
    "exam_id": 64,
    "name": "Bài tập trắc nghiệm phân biệt 'will' và 'going to'",
    "matched": [
      "2353",
      "2354",
      "2355",
      "2356",
      "2357",
      "2358",
      "2359",
      "2360",
      "2361",
      "2362"
    ]
  },
  {
    "slug": "bai-tap-trac-nghiem-phan-biet-early-va-soon-trong-tieng-anh-tieng-anh-13",
    "exam_id": 63,
    "name": "Bài tập trắc nghiệm phân biệt 'early' và 'soon' trong tiếng anh",
    "matched": [
      "2343",
      "2344",
      "2345",
      "2346",
      "2347",
      "2348",
      "2349",
      "2350",
      "2351",
      "2352"
    ]
  },
  {
    "slug": "trac-nghiem-phan-biet-much-va-many-tieng-anh-13",
    "exam_id": 62,
    "name": "Bài tập trắc nghiệm phân biệt 'much' và 'many'",
    "matched": [
      "2333",
      "2334",
      "2335",
      "2336",
      "2337",
      "2338",
      "2339",
      "2340",
      "2341",
      "2342"
    ]
  },
  {
    "slug": "trac-nghiem-ve-mao-tu-xac-dinh-trong-tieng-anh-tieng-anh-13",
    "exam_id": 60,
    "name": "Bài tập trắc nghiệm về mạo từ xác định trong tiếng Anh",
    "matched": [
      "2292",
      "2293",
      "2294",
      "2295",
      "2296",
      "2297",
      "2298",
      "2299",
      "2300",
      "2301",
      "2302",
      "2303",
      "2304",
      "2305",
      "2306",
      "2307",
      "2308",
      "2309",
      "2310",
      "2311"
    ]
  },
  {
    "slug": "trac-nghiem-phan-biet-if-va-unless-tieng-anh-13",
    "exam_id": 57,
    "name": "Bài tập trắc nghiệm phân biệt 'if' và 'unless'",
    "matched": [
      "2244",
      "2245",
      "2246",
      "2247",
      "2248",
      "2249",
      "2250",
      "2251",
      "2252",
      "2253",
      "2254",
      "2255",
      "2256",
      "2257"
    ]
  },
  {
    "slug": "bai-tap-trac-nghiem-thi-hien-tai-tiep-dien-tieng-anh-13",
    "exam_id": 53,
    "name": "Bài tập trắc nghiệm thì hiện tại tiếp diễn (Present Continuous) online",
    "matched": [
      "2108",
      "2109",
      "2110",
      "2111",
      "2112",
      "2678",
      "2679",
      "2680",
      "2681",
      "2682",
      "2683",
      "2684",
      "2685",
      "2686",
      "2687",
      "2688",
      "2689",
      "2690",
      "2691",
      "2692"
    ]
  }
]